{
  "project_info": {
    "project_number": "205297378995",
    "project_id": "parking-slot-70d3b",
    "storage_bucket": "parking-slot-70d3b.appspot.com"
  },
  "client": [
    {
      "client_info": {
        "mobilesdk_app_id": "1:205297378995:android:d1643fa646d961a8bff2c6",
        "android_client_info": {
          "package_name": "org.binaryitplanet.parking_slot_seller"
        }
      },
      "oauth_client": [
        {
          "client_id": "205297378995-jco48c2gqqsl3fusdfnec48gg4hmeh6c.apps.googleusercontent.com",
          "client_type": 3
        }
      ],
      "api_key": [
        {
          "current_key": "AIzaSyCtVKTge9ejnaooqODk_1mTE4E8bL6uJ_o"
        }
      ],
      "services": {
        "appinvite_service": {
          "other_platform_oauth_client": [
            {
              "client_id": "205297378995-jco48c2gqqsl3fusdfnec48gg4hmeh6c.apps.googleusercontent.com",
              "client_type": 3
            }
          ]
        }
      }
    }
  ],
  "configuration_version": "1"
}